_libparsingpy2_7_gcc
libparsing
