Metadata-Version: 1.1
Name: libparsing
Version: 0.9.2
Summary: Python wrapper for libparsing, a PEG-based parsing library written in C
Home-page: https://github.com/sebastien/libparsing
Author: Sébastien Pierre
Author-email: sebastien.pierre@gmail.com
License: BSD
Keywords: parsing PEG grammar libparsing
Platform: UNKNOWN
Classifier: Development Status :: 4 - Beta
Classifier: Intended Audience :: Developers
Classifier: Topic :: Software Development :: Build Tools
Classifier: License :: OSI Approved :: BSD License
Classifier: Programming Language :: Python :: 2
Classifier: Programming Language :: Python :: 2.7
Classifier: Programming Language :: Python :: 3
Classifier: Programming Language :: Python :: 3.4
